autora/experiment_runner/recruitment_manager/prolific/__init__.py
autora_experiment_runner_recruitment_manager_prolific-1.0.1.dist-info/LICENSE
autora_experiment_runner_recruitment_manager_prolific-1.0.1.dist-info/METADATA
autora_experiment_runner_recruitment_manager_prolific-1.0.1.dist-info/WHEEL
autora_experiment_runner_recruitment_manager_prolific-1.0.1.dist-info/top_level.txt
autora_experiment_runner_recruitment_manager_prolific-1.0.1.dist-info/RECORD
