Metadata-Version: 2.1
Name: autora-experiment-runner-recruitment-manager-prolific
Version: 1.0.1
Summary: AutoRA Prolific Recruitment Manager provides functionality to recruit participants via Prolific to set up an experiment runner for AutoRA
Author-email: Kevin Phan <kphan@princeton.edu>, Younes Strittmatter <younes_strittmatter@brown.edu>
License: MIT License
Project-URL: homepage, http://www.empiricalresearch.ai
Project-URL: repository, https://github.com/AutoResearch/autora-experiment-runner-recruitment-manager-prolific
Project-URL: documentation, https://autoresearch.github.io/autora/
Requires-Python: <4,>=3.8
License-File: LICENSE
Requires-Dist: autora-core
Provides-Extra: dev
Requires-Dist: autora-core[dev]; extra == "dev"
